Metadata-Version: 2.1
Name: new-relic-logger
Version: 0.3
Summary: NewRelic logger with headerless logging api
Home-page: https://github.com/TitanX-AI/new-relic-logger
Author: Kris Chou
Author-email: krischou.me@gmail.com
License: MIT
Keywords: new relic,logger,headerless api
Platform: UNKNOWN
Classifier: Development Status :: 3 - Alpha
Classifier: Intended Audience :: Developers
Classifier: Topic :: Software Development :: Build Tools
Classifier: License :: OSI Approved :: MIT License
Classifier: Programming Language :: Python :: 3
Classifier: Programming Language :: Python :: 3.7
Classifier: Programming Language :: Python :: 3.8
Classifier: Programming Language :: Python :: 3.9
Classifier: Programming Language :: Python :: 3.10
Classifier: Programming Language :: Python :: 3 :: Only
Requires-Python: >=3.7, <4
